argonaut/__init__.py
argonaut/arguments.py
argonaut/core.py
argonaut/decorators.py
argonaut/exceptions.py
argonaut/fancy_output.py
argonaut/input_sanitizer.py
argonaut/logging.py
argonaut/plugins.py
argonaut/shell_completion.py
argonaut/utils.py
argonautCli-1.2.0.dist-info/LICENSE.md
argonautCli-1.2.0.dist-info/METADATA
argonautCli-1.2.0.dist-info/WHEEL
argonautCli-1.2.0.dist-info/top_level.txt
argonautCli-1.2.0.dist-info/RECORD
